genpl/_version.py
genpl/genpl.py
genpl-1.1.1.dist-info/LICENSE.txt
genpl-1.1.1.dist-info/METADATA
genpl-1.1.1.dist-info/WHEEL
genpl-1.1.1.dist-info/entry_points.txt
genpl-1.1.1.dist-info/top_level.txt
genpl-1.1.1.dist-info/RECORD
