Metadata-Version: 2.1
Name: genpl
Version: 1.1.1
Summary: A Python script for recursively creating audio playlists
Home-page: https://github.com/dgasaway/genpl
Author: David Gasaway
Author-email: dave@gasaway.org
License: GNU GPL v2
Download-URL: https://github.com/dgasaway/genpl/releases
Keywords: audio music playlist
Platform: UNKNOWN
Classifier: Operating System :: OS Independent
Classifier: Programming Language :: Python :: 3
Classifier: License :: OSI Approved :: GNU General Public License v2 or later (GPLv2+)
Classifier: Topic :: Multimedia :: Sound/Audio
Classifier: Development Status :: 5 - Production/Stable
Classifier: Environment :: Console
Classifier: Intended Audience :: End Users/Desktop
Requires-Python: >=3
